.gitignore
LICENSE
PKGBUILD
README.md
setup.py
examples/jotdown-bake.py
examples/test-sudo-outsider.py
examples/test-sudo.py
panifex/__init__.py
panifex/bake.py
panifex/build.py
panifex/config.py
panifex/errors.py
panifex/recipes.py
panifex/reports.py
panifex/shell.py
panifex/util.py
panifex.egg-info/PKG-INFO
panifex.egg-info/SOURCES.txt
panifex.egg-info/dependency_links.txt
panifex.egg-info/entry_points.txt
panifex.egg-info/requires.txt
panifex.egg-info/top_level.txt