Metadata-Version: 2.1
Name: panifex
Version: 1.0.1
Summary: A make-like DI-based Python build system.
Home-page: https://github.com/lainproliant/panifex
Author: Lain Musgrove (lainproliant)
Author-email: lain.proliant@gmail.com
License: MIT
Keywords: build make
Platform: UNKNOWN
Classifier: Development Status :: 3 - Alpha
Classifier: Intended Audience :: Developers
Classifier: Topic :: Software Development :: Build Tools
Classifier: License :: OSI Approved :: MIT License
Classifier: Programming Language :: Python :: 3.8
